html2obj/__init__.py
html2obj/lib/__init__.py
html2obj/lib/extract.py
html2obj/lib/formathtml.py
html2obj/lib/hobj.py
html2obj/lib/html2obj.py
html2obj_genwch-0.0.8.dist-info/LICENSE
html2obj_genwch-0.0.8.dist-info/METADATA
html2obj_genwch-0.0.8.dist-info/WHEEL
html2obj_genwch-0.0.8.dist-info/top_level.txt
html2obj_genwch-0.0.8.dist-info/RECORD
