Metadata-Version: 2.1
Name: html2obj-genwch
Version: 0.0.8
Summary: A small example package
Home-page: https://github.com/genwch/html2obj
Author: genwch
Author-email: 
License: UNKNOWN
Platform: UNKNOWN
Classifier: Programming Language :: Python :: 3
Classifier: License :: OSI Approved :: MIT License
Classifier: Operating System :: OS Independent
Requires-Python: >=3.7
Requires-Dist: requests
